Metadata-Version: 1.1
Name: vimeo-dl
Version: 1.0
Summary: Retrieve Vimeo content and metadata
Home-page: https://github.com/r0oth3x49/vimeo
Author: Nasir khan (r0ot h3x49)
Author-email: r0ot@h3x49@gmail.com
License: LGPLv3
Download-URL: https://github.com/r0oth3x49/vimeo/tarball/1.0
Keywords: vimeo_dl,download,video
Platform: UNKNOWN
Classifier: License :: OSI Approved :: GNU Lesser General Public License v3 (LGPLv3)
Classifier: Operating System :: POSIX :: Linux
Classifier: Operating System :: MacOS
Classifier: Operating System :: MacOS :: MacOS 9
Classifier: Operating System :: MacOS :: MacOS X
Classifier: Operating System :: Microsoft
Classifier: Operating System :: Microsoft :: Windows :: Windows 7
Classifier: Operating System :: Microsoft :: Windows :: Windows XP
Classifier: Operating System :: Microsoft :: Windows :: Windows Vista
Classifier: Programming Language :: Python
Classifier: Programming Language :: Python :: 2
Classifier: Programming Language :: Python :: 2.6
Classifier: Programming Language :: Python :: 2.7
Classifier: Programming Language :: Python :: 3
Classifier: Programming Language :: Python :: 3.3
Classifier: Programming Language :: Python :: 3.4
